qibo_cloud_backends/__init__.py
qibo_cloud_backends/braket_client.py
qibo_cloud_backends/braket_translation.py
qibo_cloud_backends/ionq_client.py
qibo_cloud_backends/qibo_client.py
qibo_cloud_backends/qiskit_client.py
qibo_cloud_backends-0.0.6.dist-info/LICENSE
qibo_cloud_backends-0.0.6.dist-info/METADATA
qibo_cloud_backends-0.0.6.dist-info/WHEEL
qibo_cloud_backends-0.0.6.dist-info/RECORD
