Metadata-Version: 2.3
Name: qibo-cloud-backends
Version: 0.0.6
Summary: Qibo backends for client interface.
License: Apache-2.0
Author: The Qibo team
Requires-Python: >=3.9,<3.13
Classifier: License :: OSI Approved :: Apache Software License
Classifier: Programming Language :: Python :: 3
Classifier: Programming Language :: Python :: 3.9
Classifier: Programming Language :: Python :: 3.10
Classifier: Programming Language :: Python :: 3.11
Classifier: Programming Language :: Python :: 3.12
Classifier: Topic :: Scientific/Engineering :: Physics
Provides-Extra: aws
Provides-Extra: ionq
Requires-Dist: amazon-braket-sdk (>=1.88.3,<2.0.0) ; extra == "aws"
Requires-Dist: qibo (>=0.2.16,<0.3.0)
Requires-Dist: qibo_client (>=0.0.17,<0.0.18)
Requires-Dist: qiskit_ionq (>=0.5.4,<0.6.0) ; extra == "ionq"
Project-URL: Documentation, https://qibo.science/qibo-cloud-backends/stable
Project-URL: Homepage, https://qibo.science/
Project-URL: Repository, https://github.com/qiboteam/qibo-cloud-backends/
